LICENSE
MANIFEST.in
README.md
setup.py
PyGFET/AnalyzeData.py
PyGFET/CharactCore.py
PyGFET/CharactMultiCore.py
PyGFET/CharactMultiCorev2.py
PyGFET/DB.py
PyGFET/DBAnalyze.py
PyGFET/DBCore.py
PyGFET/DBSearch.py
PyGFET/DBXlsReport.py
PyGFET/DaqInterface.py
PyGFET/DataClass.py
PyGFET/DataStructures.py
PyGFET/ExportTools.py
PyGFET/GetFromDB_example.py
PyGFET/NoiseModel.py
PyGFET/PlotData.py
PyGFET/PlotDataClass.py
PyGFET/RecordCore.py
PyGFET/RecordPlot.py
PyGFET/RecordPlot.py.orig
PyGFET/StimCore.py
PyGFET/TrtTypesMaps.py
PyGFET/__init__.py
PyGFET.egg-info/PKG-INFO
PyGFET.egg-info/SOURCES.txt
PyGFET.egg-info/dependency_links.txt
PyGFET.egg-info/entry_points.txt
PyGFET.egg-info/requires.txt
PyGFET.egg-info/top_level.txt
PyGFET/GuiDBView/GuiDBView.py
PyGFET/GuiDBView/GuiDBView.ui
PyGFET/GuiDBView/GuiDataExplorer.ui
PyGFET/GuiDBView/__init__.py
PyGFET/GuiMeasure/GuiCharact.py
PyGFET/GuiMeasure/GuiCharact.ui
PyGFET/GuiMeasure/__init__.py
PyGFET/GuiMultiChannel/GuiCharactMulti.py
PyGFET/GuiMultiChannel/GuiCharactMulti.ui
PyGFET/GuiMultiChannel/GuiCharactMultiv2.ui
PyGFET/GuiMultiChannel/__init__.py
PyGFET/GuiRecordView/GuiRecordExplorer.py
PyGFET/GuiRecordView/GuiRecordExplorer.ui
PyGFET/GuiRecordView/__init__.py
PyGFET/GuiStimulation/GuiStim.py
PyGFET/GuiStimulation/GuiStim.ui
PyGFET/GuiStimulation/__init__.py