Metadata-Version: 1.2
Name: PyGFET
Version: 0.1.3
Summary: GFET Analysis tools
Home-page: https://github.com/aguimera/PyGFET
Author: Anton Guimera-Brunet
Author-email: anton.guimera@csic.es
Maintainer: Anton Guimera-Brunet
Maintainer-email: anton.guimera@csic.es
License: GPLv3
Download-URL: https://github.com/aguimera/PyGFET
Platform: UNKNOWN
Classifier: Development Status :: 3 - Alpha
Classifier: Environment :: Console
Classifier: Environment :: X11 Applications :: Qt
Classifier: Environment :: Win32 (MS Windows)
Classifier: Intended Audience :: Science/Research
Classifier: License :: OSI Approved :: GNU General Public License (GPL)
Classifier: Operating System :: Microsoft :: Windows
Classifier: Operating System :: POSIX
Classifier: Operating System :: POSIX :: Linux
Classifier: Operating System :: Unix
Classifier: Operating System :: OS Independent
Classifier: Programming Language :: Python
Classifier: Programming Language :: Python :: 2.7
Classifier: Topic :: Scientific/Engineering
Classifier: Topic :: Software Development :: User Interfaces
